gradle.properties
hexdoc_hexparse/__gradle_version__.py
hexdoc_hexparse/__init__.py
hexdoc_hexparse/__version__.py
hexdoc_hexparse/_hooks.py
hexdoc_hexparse/py.typed
hexdoc_hexparse/_export/.gitignore
hexdoc_hexparse/_export/__init__.py
hexdoc_hexparse/_export/generated/__init__.py
hexdoc_hexparse/_export/generated/hexparse.hexdoc.json
hexdoc_hexparse/_export/generated/hexparse.patterns.hexdoc.json
hexdoc_hexparse/_export/generated/assets/hexcasting/patchouli_books/thehexbook/en_us/categories/hexparse/commands.json
hexdoc_hexparse/_export/generated/assets/hexcasting/patchouli_books/thehexbook/en_us/entries/hexparse_commands/config.json
hexdoc_hexparse/_export/generated/assets/hexcasting/patchouli_books/thehexbook/en_us/entries/hexparse_commands/io.json
hexdoc_hexparse/_export/generated/assets/hexcasting/patchouli_books/thehexbook/en_us/entries/hexparse_commands/misc.json
hexdoc_hexparse/_export/generated/assets/hexcasting/patchouli_books/thehexbook/en_us/entries/hexparse_commands/op.json
hexdoc_hexparse/_export/generated/assets/hexcasting/patchouli_books/thehexbook/en_us/entries/patterns/hexparse.json
hexdoc_hexparse/_export/generated/assets/hexparse/lang/en_us.flatten.json5
hexdoc_hexparse/_export/generated/assets/hexparse/lang/en_us.json
hexdoc_hexparse/_export/generated/assets/hexparse/lang/zh_cn.json
hexdoc_hexparse/_export/generated/data/hexcasting/tags/action/per_world_pattern.json
hexdoc_hexparse/_templates/__init__.py
hexdoc_hexparse-1.6.0.1.1.dist-info/METADATA
hexdoc_hexparse-1.6.0.1.1.dist-info/WHEEL
hexdoc_hexparse-1.6.0.1.1.dist-info/entry_points.txt
hexdoc_hexparse-1.6.0.1.1.dist-info/licenses/LICENSE.txt
hexdoc_hexparse-1.6.0.1.1.dist-info/RECORD
